markupy_htmx/__init__.py
markupy_htmx/attributes.py
markupy_htmx/py.typed
markupy_htmx/_private/__init__.py
markupy_htmx/_private/htmx.py
markupy_htmx-1.1.1.dist-info/licenses/LICENSE
markupy_htmx-1.1.1.dist-info/WHEEL
markupy_htmx-1.1.1.dist-info/METADATA
markupy_htmx-1.1.1.dist-info/RECORD
