Metadata-Version: 2.4
Name: markupy_htmx
Version: 1.1.1
Summary: An HTMX extension for markupy
Author-email: witiz <markupy@witiz.com>
Requires-Python: >=3.10
Classifier: Programming Language :: Python :: 3
Classifier: License :: OSI Approved :: MIT License
Classifier: Intended Audience :: Developers
Classifier: Development Status :: 5 - Production/Stable
Classifier: Topic :: Text Processing :: Markup :: HTML
Classifier: Operating System :: OS Independent
Classifier: Typing :: Typed
License-File: LICENSE
Requires-Dist: markupy>=2.1.0
Project-URL: Issues, https://github.com/witiz/markupy_htmx/issues
Project-URL: Repository, https://github.com/witiz/markupy_htmx
